LICENSE.txt
MANIFEST.in
README.rst
setup.py
faCRSA/.flaskenv
faCRSA/huey_consumer.py
faCRSA/start_queue.py
faCRSA/start_web.py
faCRSA/taskQueue.py
faCRSA/tasks.py
faCRSA.egg-info/PKG-INFO
faCRSA.egg-info/SOURCES.txt
faCRSA.egg-info/dependency_links.txt
faCRSA.egg-info/entry_points.txt
faCRSA.egg-info/requires.txt
faCRSA.egg-info/top_level.txt
faCRSA/facrsa_code/__init__.py
faCRSA/facrsa_code/library/__init__.py
faCRSA/facrsa_code/library/analysis/__init__.py
faCRSA/facrsa_code/library/analysis/config.ini
faCRSA/facrsa_code/library/analysis/config.py
faCRSA/facrsa_code/library/analysis/errorcheck.py
faCRSA/facrsa_code/library/analysis/interact.py
faCRSA/facrsa_code/library/analysis/main.py
faCRSA/facrsa_code/library/analysis/postaction.py
faCRSA/facrsa_code/library/analysis/predict.py
faCRSA/facrsa_code/library/analysis/processing.py
faCRSA/facrsa_code/library/analysis/rootanalysis.py
faCRSA/facrsa_code/library/analysis/start.py
faCRSA/facrsa_code/library/analysis/database/__init__.py
faCRSA/facrsa_code/library/analysis/database/writermysql.py
faCRSA/facrsa_code/library/analysis/net/__init__.py
faCRSA/facrsa_code/library/analysis/net/rootseg/RootSeg.py
faCRSA/facrsa_code/library/analysis/net/rootseg/__init__.py
faCRSA/facrsa_code/library/analysis/net/rootseg/attention.py
faCRSA/facrsa_code/library/analysis/net/rootseg/weight/__init__.py
faCRSA/facrsa_code/library/analysis/net/rootseg/weight/all.h5
faCRSA/facrsa_code/library/analysis/net/rootseg/weight/main.h5
faCRSA/facrsa_code/library/util/__init__.py
faCRSA/facrsa_code/library/util/configUtil.py
faCRSA/facrsa_code/library/util/sqliteUtil.py
faCRSA/facrsa_code/library/web/__init__.py
faCRSA/facrsa_code/library/web/dataApi.py
faCRSA/facrsa_code/library/web/views.py
faCRSA/facrsa_code/static/__init__.py
faCRSA/facrsa_code/static/assets/aiphenomics.png
faCRSA/facrsa_code/static/assets/facrsa.png
faCRSA/facrsa_code/static/assets/favicon.ico
faCRSA/facrsa_code/static/assets/linux.svg
faCRSA/facrsa_code/static/assets/mac.svg
faCRSA/facrsa_code/static/assets/njau.png
faCRSA/facrsa_code/static/assets/windows.svg
faCRSA/facrsa_code/static/css/bootstrap-icons.css
