Metadata-Version: 2.1
Name: faCRSA
Version: 1.0.4
Summary: faCRSA
Home-page: https://zrn0.top/
Author: Ruinan Zhang
Author-email: hellozrn9@gmail.com
License: MIT License
Platform: all
Classifier: Intended Audience :: Developers
Classifier: Operating System :: OS Independent
Classifier: Natural Language :: Chinese (Simplified)
Classifier: Programming Language :: Python
Classifier: Programming Language :: Python :: 3.6
Classifier: Programming Language :: Python :: 3.7
Classifier: Programming Language :: Python :: 3.8
Classifier: Topic :: Software Development :: Libraries
License-File: LICENSE.txt
